{
  "books": [
    {"title": "To Kill a Mockingbird", "author": "Harper Lee", "genre": "fiction"},
    {"title": "1984", "author": "George Orwell", "genre": "fiction"},
    {"title": "Pride and Prejudice", "author": "Jane Austen", "genre": "fiction"},
    {"title": "The Great Gatsby", "author": "F. Scott Fitzgerald", "genre": "fiction"},
    {"title": "One Hundred Years of Solitude", "author": "Gabriel García Márquez", "genre": "fiction"},
    {"title": "Brave New World", "author": "Aldous Huxley", "genre": "fiction"},
    {"title": "The Catcher in the Rye", "author": "J.D. Salinger", "genre": "fiction"},
    {"title": "Lord of the Flies", "author": "William Golding", "genre": "fiction"},
    {"title": "Animal Farm", "author": "George Orwell", "genre": "fiction"},
    {"title": "The Alchemist", "author": "Paulo Coelho", "genre": "fiction"},
    {"title": "The Road", "author": "Cormac McCarthy", "genre": "fiction"},
    {"title": "Crime and Punishment", "author": "Fyodor Dostoevsky", "genre": "fiction"},
    {"title": "War and Peace", "author": "Leo Tolstoy", "genre": "fiction"},
    {"title": "The Brothers Karamazov", "author": "Fyodor Dostoevsky", "genre": "fiction"},
    {"title": "Don Quixote", "author": "Miguel de Cervantes", "genre": "fiction"},
    {"title": "Les Misérables", "author": "Victor Hugo", "genre": "fiction"},
    {"title": "Moby-Dick", "author": "Herman Melville", "genre": "fiction"},
    {"title": "Great Expectations", "author": "Charles Dickens", "genre": "fiction"},
    {"title": "The Count of Monte Cristo", "author": "Alexandre Dumas", "genre": "fiction"},
    {"title": "Anna Karenina", "author": "Leo Tolstoy", "genre": "fiction"},
    {"title": "The Little Prince", "author": "Antoine de Saint-Exupéry", "genre": "fiction"},
    {"title": "Catch-22", "author": "Joseph Heller", "genre": "fiction"},
    {"title": "Slaughterhouse-Five", "author": "Kurt Vonnegut", "genre": "fiction"},
    {"title": "Beloved", "author": "Toni Morrison", "genre": "fiction"},
    {"title": "The Grapes of Wrath", "author": "John Steinbeck", "genre": "fiction"},
    {"title": "Invisible Man", "author": "Ralph Ellison", "genre": "fiction"},
    {"title": "A Tale of Two Cities", "author": "Charles Dickens", "genre": "fiction"},
    {"title": "The Bell Jar", "author": "Sylvia Plath", "genre": "fiction"},
    {"title": "Their Eyes Were Watching God", "author": "Zora Neale Hurston", "genre": "fiction"},
    {"title": "The Kite Runner", "author": "Khaled Hosseini", "genre": "fiction"},
    {"title": "Of Mice and Men", "author": "John Steinbeck", "genre": "fiction"},
    {"title": "The Color Purple", "author": "Alice Walker", "genre": "fiction"},
    {"title": "The Old Man and the Sea", "author": "Ernest Hemingway", "genre": "fiction"},
    {"title": "A Farewell to Arms", "author": "Ernest Hemingway", "genre": "fiction"},
    {"title": "Lolita", "author": "Vladimir Nabokov", "genre": "fiction"},
    {"title": "The Sound and the Fury", "author": "William Faulkner", "genre": "fiction"},
    {"title": "On the Road", "author": "Jack Kerouac", "genre": "fiction"},
    {"title": "The Handmaid's Tale", "author": "Margaret Atwood", "genre": "fiction"},
    {"title": "Normal People", "author": "Sally Rooney", "genre": "fiction"},
    {"title": "A Thousand Splendid Suns", "author": "Khaled Hosseini", "genre": "fiction"},

    {"title": "The Hobbit", "author": "J.R.R. Tolkien", "genre": "fantasy"},
    {"title": "Harry Potter and the Sorcerer's Stone", "author": "J.K. Rowling", "genre": "fantasy"},
    {"title": "The Lord of the Rings", "author": "J.R.R. Tolkien", "genre": "fantasy"},
    {"title": "A Game of Thrones", "author": "George R.R. Martin", "genre": "fantasy"},
    {"title": "The Name of the Wind", "author": "Patrick Rothfuss", "genre": "fantasy"},
    {"title": "The Chronicles of Narnia", "author": "C.S. Lewis", "genre": "fantasy"},
    {"title": "A Wizard of Earthsea", "author": "Ursula K. Le Guin", "genre": "fantasy"},
    {"title": "The Wheel of Time: The Eye of the World", "author": "Robert Jordan", "genre": "fantasy"},
    {"title": "The Way of Kings", "author": "Brandon Sanderson", "genre": "fantasy"},
    {"title": "Mistborn: The Final Empire", "author": "Brandon Sanderson", "genre": "fantasy"},
    {"title": "American Gods", "author": "Neil Gaiman", "genre": "fantasy"},
    {"title": "Good Omens", "author": "Terry Pratchett & Neil Gaiman", "genre": "fantasy"},
    {"title": "The Color of Magic", "author": "Terry Pratchett", "genre": "fantasy"},
    {"title": "The Lies of Locke Lamora", "author": "Scott Lynch", "genre": "fantasy"},
    {"title": "The Blade Itself", "author": "Joe Abercrombie", "genre": "fantasy"},
    {"title": "Assassin's Apprentice", "author": "Robin Hobb", "genre": "fantasy"},
    {"title": "The Fifth Season", "author": "N.K. Jemisin", "genre": "fantasy"},
    {"title": "Eragon", "author": "Christopher Paolini", "genre": "fantasy"},
    {"title": "The Silmarillion", "author": "J.R.R. Tolkien", "genre": "fantasy"},
    {"title": "Gardens of the Moon", "author": "Steven Erikson", "genre": "fantasy"},
    {"title": "The Once and Future King", "author": "T.H. White", "genre": "fantasy"},
    {"title": "Piranesi", "author": "Susanna Clarke", "genre": "fantasy"},
    {"title": "The Night Circus", "author": "Erin Morgenstern", "genre": "fantasy"},
    {"title": "Stardust", "author": "Neil Gaiman", "genre": "fantasy"},
    {"title": "The Poppy War", "author": "R.F. Kuang", "genre": "fantasy"},

    {"title": "Dune", "author": "Frank Herbert", "genre": "scifi"},
    {"title": "Ender's Game", "author": "Orson Scott Card", "genre": "scifi"},
    {"title": "The Hitchhiker's Guide to the Galaxy", "author": "Douglas Adams", "genre": "scifi"},
    {"title": "Foundation", "author": "Isaac Asimov", "genre": "scifi"},
    {"title": "Neuromancer", "author": "William Gibson", "genre": "scifi"},
    {"title": "The Hunger Games", "author": "Suzanne Collins", "genre": "scifi"},
    {"title": "Fahrenheit 451", "author": "Ray Bradbury", "genre": "scifi"},
    {"title": "The Left Hand of Darkness", "author": "Ursula K. Le Guin", "genre": "scifi"},
    {"title": "2001: A Space Odyssey", "author": "Arthur C. Clarke", "genre": "scifi"},
    {"title": "Snow Crash", "author": "Neal Stephenson", "genre": "scifi"},
    {"title": "The Martian", "author": "Andy Weir", "genre": "scifi"},
    {"title": "Childhood's End", "author": "Arthur C. Clarke", "genre": "scifi"},
    {"title": "Do Androids Dream of Electric Sheep?", "author": "Philip K. Dick", "genre": "scifi"},
    {"title": "The Time Machine", "author": "H.G. Wells", "genre": "scifi"},
    {"title": "The War of the Worlds", "author": "H.G. Wells", "genre": "scifi"},
    {"title": "Hyperion", "author": "Dan Simmons", "genre": "scifi"},
    {"title": "Solaris", "author": "Stanislaw Lem", "genre": "scifi"},
    {"title": "Rendezvous with Rama", "author": "Arthur C. Clarke", "genre": "scifi"},
    {"title": "The Expanse: Leviathan Wakes", "author": "James S.A. Corey", "genre": "scifi"},
    {"title": "Project Hail Mary", "author": "Andy Weir", "genre": "scifi"},
    {"title": "Red Mars", "author": "Kim Stanley Robinson", "genre": "scifi"},
    {"title": "The Dispossessed", "author": "Ursula K. Le Guin", "genre": "scifi"},
    {"title": "Ringworld", "author": "Larry Niven", "genre": "scifi"},
    {"title": "Contact", "author": "Carl Sagan", "genre": "scifi"},
    {"title": "The Three-Body Problem", "author": "Liu Cixin", "genre": "scifi"},

    {"title": "The Shining", "author": "Stephen King", "genre": "horror"},
    {"title": "Dracula", "author": "Bram Stoker", "genre": "horror"},
    {"title": "Frankenstein", "author": "Mary Shelley", "genre": "horror"},
    {"title": "It", "author": "Stephen King", "genre": "horror"},
    {"title": "The Haunting of Hill House", "author": "Shirley Jackson", "genre": "horror"},
    {"title": "Pet Sematary", "author": "Stephen King", "genre": "horror"},
    {"title": "The Exorcist", "author": "William Peter Blatty", "genre": "horror"},
    {"title": "House of Leaves", "author": "Mark Z. Danielewski", "genre": "horror"},
    {"title": "The Turn of the Screw", "author": "Henry James", "genre": "horror"},
    {"title": "Bird Box", "author": "Josh Malerman", "genre": "horror"},
    {"title": "The Silence of the Lambs", "author": "Thomas Harris", "genre": "horror"},
    {"title": "Mexican Gothic", "author": "Silvia Moreno-Garcia", "genre": "horror"},
    {"title": "We Have Always Lived in the Castle", "author": "Shirley Jackson", "genre": "horror"},
    {"title": "The Strange Case of Dr. Jekyll and Mr. Hyde", "author": "Robert Louis Stevenson", "genre": "horror"},
    {"title": "Rosemary's Baby", "author": "Ira Levin", "genre": "horror"},
    {"title": "Misery", "author": "Stephen King", "genre": "horror"},
    {"title": "Carrie", "author": "Stephen King", "genre": "horror"},

    {"title": "Murder on the Orient Express", "author": "Agatha Christie", "genre": "mystery"},
    {"title": "The Girl with the Dragon Tattoo", "author": "Stieg Larsson", "genre": "mystery"},
    {"title": "Gone Girl", "author": "Gillian Flynn", "genre": "mystery"},
    {"title": "And Then There Were None", "author": "Agatha Christie", "genre": "mystery"},
    {"title": "The Da Vinci Code", "author": "Dan Brown", "genre": "mystery"},
    {"title": "The Hound of the Baskervilles", "author": "Arthur Conan Doyle", "genre": "mystery"},
    {"title": "Big Little Lies", "author": "Liane Moriarty", "genre": "mystery"},
    {"title": "In the Woods", "author": "Tana French", "genre": "mystery"},
    {"title": "The Girl on the Train", "author": "Paula Hawkins", "genre": "mystery"},
    {"title": "Rebecca", "author": "Daphne du Maurier", "genre": "mystery"},
    {"title": "Sharp Objects", "author": "Gillian Flynn", "genre": "mystery"},
    {"title": "The Maltese Falcon", "author": "Dashiell Hammett", "genre": "mystery"},
    {"title": "The Big Sleep", "author": "Raymond Chandler", "genre": "mystery"},
    {"title": "The Woman in the Window", "author": "A.J. Finn", "genre": "mystery"},
    {"title": "The Silent Patient", "author": "Alex Michaelides", "genre": "mystery"},
    {"title": "The No. 1 Ladies' Detective Agency", "author": "Alexander McCall Smith", "genre": "mystery"},

    {"title": "Sapiens", "author": "Yuval Noah Harari", "genre": "nonfiction"},
    {"title": "Thinking, Fast and Slow", "author": "Daniel Kahneman", "genre": "nonfiction"},
    {"title": "Atomic Habits", "author": "James Clear", "genre": "nonfiction"},
    {"title": "Educated", "author": "Tara Westover", "genre": "nonfiction"},
    {"title": "The Power of Habit", "author": "Charles Duhigg", "genre": "nonfiction"},
    {"title": "A Brief History of Time", "author": "Stephen Hawking", "genre": "nonfiction"},
    {"title": "Becoming", "author": "Michelle Obama", "genre": "nonfiction"},
    {"title": "The Art of War", "author": "Sun Tzu", "genre": "nonfiction"},
    {"title": "Meditations", "author": "Marcus Aurelius", "genre": "nonfiction"},
    {"title": "Outliers", "author": "Malcolm Gladwell", "genre": "nonfiction"},
    {"title": "Guns, Germs, and Steel", "author": "Jared Diamond", "genre": "nonfiction"},
    {"title": "The Selfish Gene", "author": "Richard Dawkins", "genre": "nonfiction"},
    {"title": "Freakonomics", "author": "Steven D. Levitt & Stephen J. Dubner", "genre": "nonfiction"},
    {"title": "Quiet: The Power of Introverts", "author": "Susan Cain", "genre": "nonfiction"},
    {"title": "The Immortal Life of Henrietta Lacks", "author": "Rebecca Skloot", "genre": "nonfiction"},
    {"title": "Cosmos", "author": "Carl Sagan", "genre": "nonfiction"},
    {"title": "The Sixth Extinction", "author": "Elizabeth Kolbert", "genre": "nonfiction"},
    {"title": "Bad Blood", "author": "John Carreyrou", "genre": "nonfiction"},
    {"title": "Silent Spring", "author": "Rachel Carson", "genre": "nonfiction"},
    {"title": "The Emperor of All Maladies", "author": "Siddhartha Mukherjee", "genre": "nonfiction"},
    {"title": "Homo Deus", "author": "Yuval Noah Harari", "genre": "nonfiction"},

    {"title": "Jane Eyre", "author": "Charlotte Brontë", "genre": "romance"},
    {"title": "Wuthering Heights", "author": "Emily Brontë", "genre": "romance"},
    {"title": "The Notebook", "author": "Nicholas Sparks", "genre": "romance"},
    {"title": "Me Before You", "author": "Jojo Moyes", "genre": "romance"},
    {"title": "Outlander", "author": "Diana Gabaldon", "genre": "romance"},
    {"title": "The Bridges of Madison County", "author": "Robert James Waller", "genre": "romance"},
    {"title": "The Thorn Birds", "author": "Colleen McCullough", "genre": "romance"},
    {"title": "A Walk to Remember", "author": "Nicholas Sparks", "genre": "romance"},
    {"title": "The Time Traveler's Wife", "author": "Audrey Niffenegger", "genre": "romance"},
    {"title": "Atonement", "author": "Ian McEwan", "genre": "romance"},
    {"title": "Beach Read", "author": "Emily Henry", "genre": "romance"},
    {"title": "People We Meet on Vacation", "author": "Emily Henry", "genre": "romance"},
    {"title": "The Hating Game", "author": "Sally Thorne", "genre": "romance"},
    {"title": "It Ends with Us", "author": "Colleen Hoover", "genre": "romance"},
    {"title": "The Rosie Project", "author": "Graeme Simsion", "genre": "romance"},
    {"title": "Red, White & Royal Blue", "author": "Casey McQuiston", "genre": "romance"},

    {"title": "Steve Jobs", "author": "Walter Isaacson", "genre": "biography"},
    {"title": "The Diary of a Young Girl", "author": "Anne Frank", "genre": "biography"},
    {"title": "Long Walk to Freedom", "author": "Nelson Mandela", "genre": "biography"},
    {"title": "The Autobiography of Malcolm X", "author": "Malcolm X & Alex Haley", "genre": "biography"},
    {"title": "Leonardo da Vinci", "author": "Walter Isaacson", "genre": "biography"},
    {"title": "Alexander Hamilton", "author": "Ron Chernow", "genre": "biography"},
    {"title": "Einstein: His Life and Universe", "author": "Walter Isaacson", "genre": "biography"},
    {"title": "Unbroken", "author": "Laura Hillenbrand", "genre": "biography"},
    {"title": "When Breath Becomes Air", "author": "Paul Kalanithi", "genre": "biography"},
    {"title": "Born a Crime", "author": "Trevor Noah", "genre": "biography"},
    {"title": "I Know Why the Caged Bird Sings", "author": "Maya Angelou", "genre": "biography"},
    {"title": "Shoe Dog", "author": "Phil Knight", "genre": "biography"},
    {"title": "Open", "author": "Andre Agassi", "genre": "biography"},
    {"title": "The Glass Castle", "author": "Jeannette Walls", "genre": "biography"},
    {"title": "Man's Search for Meaning", "author": "Viktor E. Frankl", "genre": "biography"},
    {"title": "Benjamin Franklin: An American Life", "author": "Walter Isaacson", "genre": "biography"},

    {"title": "A People's History of the United States", "author": "Howard Zinn", "genre": "history"},
    {"title": "The Rise and Fall of the Third Reich", "author": "William L. Shirer", "genre": "history"},
    {"title": "1776", "author": "David McCullough", "genre": "history"},
    {"title": "The Silk Roads", "author": "Peter Frankopan", "genre": "history"},
    {"title": "SPQR: A History of Ancient Rome", "author": "Mary Beard", "genre": "history"},
    {"title": "The Histories", "author": "Herodotus", "genre": "history"},
    {"title": "Team of Rivals", "author": "Doris Kearns Goodwin", "genre": "history"},
    {"title": "The Wright Brothers", "author": "David McCullough", "genre": "history"},
    {"title": "Genghis Khan and the Making of the Modern World", "author": "Jack Weatherford", "genre": "history"},
    {"title": "Bury My Heart at Wounded Knee", "author": "Dee Brown", "genre": "history"},
    {"title": "The Guns of August", "author": "Barbara W. Tuchman", "genre": "history"},

    {"title": "How to Win Friends and Influence People", "author": "Dale Carnegie", "genre": "selfhelp"},
    {"title": "The 7 Habits of Highly Effective People", "author": "Stephen R. Covey", "genre": "selfhelp"},
    {"title": "Think and Grow Rich", "author": "Napoleon Hill", "genre": "selfhelp"},
    {"title": "The Subtle Art of Not Giving a F*ck", "author": "Mark Manson", "genre": "selfhelp"},
    {"title": "You Are a Badass", "author": "Jen Sincero", "genre": "selfhelp"},
    {"title": "Daring Greatly", "author": "Brené Brown", "genre": "selfhelp"},
    {"title": "The Four Agreements", "author": "Don Miguel Ruiz", "genre": "selfhelp"},
    {"title": "Mindset: The New Psychology of Success", "author": "Carol S. Dweck", "genre": "selfhelp"},
    {"title": "The Power of Now", "author": "Eckhart Tolle", "genre": "selfhelp"},
    {"title": "Grit: The Power of Passion and Perseverance", "author": "Angela Duckworth", "genre": "selfhelp"},
    {"title": "Rich Dad Poor Dad", "author": "Robert T. Kiyosaki", "genre": "selfhelp"},
    {"title": "Deep Work", "author": "Cal Newport", "genre": "selfhelp"},
    {"title": "The Miracle Morning", "author": "Hal Elrod", "genre": "selfhelp"},
    {"title": "Emotional Intelligence", "author": "Daniel Goleman", "genre": "selfhelp"},
    {"title": "Start with Why", "author": "Simon Sinek", "genre": "selfhelp"},

    {"title": "Charlotte's Web", "author": "E.B. White", "genre": "children"},
    {"title": "Where the Wild Things Are", "author": "Maurice Sendak", "genre": "children"},
    {"title": "The Very Hungry Caterpillar", "author": "Eric Carle", "genre": "children"},
    {"title": "Matilda", "author": "Roald Dahl", "genre": "children"},
    {"title": "Charlie and the Chocolate Factory", "author": "Roald Dahl", "genre": "children"},
    {"title": "The Cat in the Hat", "author": "Dr. Seuss", "genre": "children"},
    {"title": "Green Eggs and Ham", "author": "Dr. Seuss", "genre": "children"},
    {"title": "Goodnight Moon", "author": "Margaret Wise Brown", "genre": "children"},
    {"title": "Alice's Adventures in Wonderland", "author": "Lewis Carroll", "genre": "children"},
    {"title": "The Giving Tree", "author": "Shel Silverstein", "genre": "children"},
    {"title": "A Wrinkle in Time", "author": "Madeleine L'Engle", "genre": "children"},
    {"title": "James and the Giant Peach", "author": "Roald Dahl", "genre": "children"},
    {"title": "The Phantom Tollbooth", "author": "Norton Juster", "genre": "children"},
    {"title": "Percy Jackson and the Lightning Thief", "author": "Rick Riordan", "genre": "children"},
    {"title": "Diary of a Wimpy Kid", "author": "Jeff Kinney", "genre": "children"},

    {"title": "Maus", "author": "Art Spiegelman", "genre": "comics"},
    {"title": "Watchmen", "author": "Alan Moore", "genre": "comics"},
    {"title": "Persepolis", "author": "Marjane Satrapi", "genre": "comics"},
    {"title": "The Sandman", "author": "Neil Gaiman", "genre": "comics"},
    {"title": "V for Vendetta", "author": "Alan Moore", "genre": "comics"},
    {"title": "Batman: The Dark Knight Returns", "author": "Frank Miller", "genre": "comics"},
    {"title": "Fun Home", "author": "Alison Bechdel", "genre": "comics"},
    {"title": "Saga", "author": "Brian K. Vaughan", "genre": "comics"},
    {"title": "Bone", "author": "Jeff Smith", "genre": "comics"},
    {"title": "Scott Pilgrim", "author": "Bryan Lee O'Malley", "genre": "comics"},
    {"title": "Ghost World", "author": "Daniel Clowes", "genre": "comics"},

    {"title": "The Republic", "author": "Plato", "genre": "philosophy"},
    {"title": "Beyond Good and Evil", "author": "Friedrich Nietzsche", "genre": "philosophy"},
    {"title": "Being and Nothingness", "author": "Jean-Paul Sartre", "genre": "philosophy"},
    {"title": "The Prince", "author": "Niccolò Machiavelli", "genre": "philosophy"},
    {"title": "Thus Spoke Zarathustra", "author": "Friedrich Nietzsche", "genre": "philosophy"},
    {"title": "Critique of Pure Reason", "author": "Immanuel Kant", "genre": "philosophy"},
    {"title": "The Myth of Sisyphus", "author": "Albert Camus", "genre": "philosophy"},
    {"title": "Ethics", "author": "Baruch Spinoza", "genre": "philosophy"},
    {"title": "Tao Te Ching", "author": "Lao Tzu", "genre": "philosophy"},
    {"title": "The Consolation of Philosophy", "author": "Boethius", "genre": "philosophy"},
    {"title": "Existentialism Is a Humanism", "author": "Jean-Paul Sartre", "genre": "philosophy"},
    {"title": "A History of Western Philosophy", "author": "Bertrand Russell", "genre": "philosophy"},

    {"title": "Leaves of Grass", "author": "Walt Whitman", "genre": "poetry"},
    {"title": "The Waste Land", "author": "T.S. Eliot", "genre": "poetry"},
    {"title": "Milk and Honey", "author": "Rupi Kaur", "genre": "poetry"},
    {"title": "The Odyssey", "author": "Homer", "genre": "poetry"},
    {"title": "The Iliad", "author": "Homer", "genre": "poetry"},
    {"title": "Paradise Lost", "author": "John Milton", "genre": "poetry"},
    {"title": "The Divine Comedy", "author": "Dante Alighieri", "genre": "poetry"},
    {"title": "Sonnets", "author": "William Shakespeare", "genre": "poetry"},
    {"title": "The Collected Poems of Emily Dickinson", "author": "Emily Dickinson", "genre": "poetry"},
    {"title": "Selected Poems", "author": "Pablo Neruda", "genre": "poetry"},
    {"title": "The Sun and Her Flowers", "author": "Rupi Kaur", "genre": "poetry"},
    {"title": "Ariel", "author": "Sylvia Plath", "genre": "poetry"}
  ]
}
